MANIFEST.in
setup.py
eul_doc.egg-info/PKG-INFO
eul_doc.egg-info/SOURCES.txt
eul_doc.egg-info/dependency_links.txt
eul_doc.egg-info/pbr.json
eul_doc.egg-info/requires.txt
eul_doc.egg-info/top_level.txt
euldoc/__init__.py
euldoc/__main__.py