Metadata-Version: 2.1
Name: eul-doc
Version: 2.0.2
Summary: Eul's Document Transforms
Home-page: https://github.com/boisgera/eul-doc
Author: Sébastien Boisgérault
Author-email: <Sebastien.Boisgerault@gmail.com>
License: MIT License
Platform: UNKNOWN
Classifier: Programming Language :: Python :: 3
Classifier: Operating System :: OS Independent
Classifier: License :: OSI Approved :: MIT License
Classifier: Topic :: Text Editors :: Text Processing
